benetech_annotation_parser/_version.py
benetech_annotation_parser/annotation_api.py
benetech_annotation_parser-0.0.3.dist-info/METADATA
benetech_annotation_parser-0.0.3.dist-info/WHEEL
benetech_annotation_parser-0.0.3.dist-info/licenses/LICENSE
benetech_annotation_parser-0.0.3.dist-info/RECORD
